maoyan_font/__init__.py
maoyan_font/__main__.py
maoyan_font/font.py
maoyan_font-2018.12.1.dist-info/LICENSE
maoyan_font-2018.12.1.dist-info/METADATA
maoyan_font-2018.12.1.dist-info/WHEEL
maoyan_font-2018.12.1.dist-info/entry_points.txt
maoyan_font-2018.12.1.dist-info/top_level.txt
maoyan_font-2018.12.1.dist-info/RECORD
