Metadata-Version: 2.1
Name: maoyan-font
Version: 2018.12.1
Summary: 将猫眼电影网页中票房、评分等数据的乱码转化成正常数字。
Home-page: https://github.com/digglife/maoyan-font
Author: Zhu Sheng Li
Author-email: digglife@gmail.com
License: UNKNOWN
Platform: UNKNOWN
Classifier: Environment :: Web Environment
Classifier: Programming Language :: Python :: 3
Classifier: License :: OSI Approved :: MIT License
Classifier: Operating System :: OS Independent
Classifier: Topic :: Internet :: WWW/HTTP :: Dynamic Content
Requires-Dist: requests
Requires-Dist: fonttools
Requires-Dist: beautifulsoup4
